tshistory_editor/__init__.py
tshistory_editor/app.py
tshistory_editor/cli.py
tshistory_editor/command.py
tshistory_editor/editor.py
tshistory_editor-0.8.2.dist-info/METADATA
tshistory_editor-0.8.2.dist-info/WHEEL
tshistory_editor-0.8.2.dist-info/top_level.txt
tshistory_editor-0.8.2.dist-info/RECORD
